parmesan/.gitignore
parmesan/__init__.py
parmesan/accessor.py
parmesan/aggregate.py
parmesan/analysis.py
parmesan/bounds.py
parmesan/clouds.py
parmesan/errors.py
parmesan/flux.py
parmesan/stability.py
parmesan/stats.py
parmesan/symbols.py
parmesan/turbulence.py
parmesan/units.py
parmesan/vector.py
parmesan/wind.py
parmesan/gas/__init__.py
parmesan/gas/constants.py
parmesan/gas/conversion.py
parmesan/gas/density.py
parmesan/gas/humidity.py
parmesan/gas/laws.py
parmesan/gas/pressure.py
parmesan/gas/temperature.py
parmesan/processing/__init__.py
parmesan/processing/cleanup.py
parmesan/radiation/__init__.py
parmesan/radiation/constants.py
parmesan/utils/__init__.py
parmesan/utils/function.py
parmesan/utils/mode.py
parmesan/utils/string.py
tests/__init__.py
tests/__main__.py
tests/test_accessor.py
tests/test_aggregate.py
tests/test_autocorrelation.py
tests/test_bounds.py
tests/test_clouds.py
tests/test_density.py
tests/test_gas_conversion.py
tests/test_humidity.py
tests/test_pressure.py
tests/test_processing_cleanup.py
tests/test_radiation.py
tests/test_spectrum.py
tests/test_stability.py
tests/test_stats.py
tests/test_structure.py
tests/test_symbols.py
tests/test_temperature.py
tests/test_turbulence.py
tests/test_units.py
tests/test_utils.py
tests/test_vector.py
tests/test_wind.py
parmesan-2.2.0.dist-info/METADATA
parmesan-2.2.0.dist-info/WHEEL
parmesan-2.2.0.dist-info/licenses/LICENSE
parmesan-2.2.0.dist-info/RECORD
