Metadata-Version: 2.4
Name: parmesan
Version: 2.2.0
Summary: Python Atmospheric Research Package for Meteorological Timeseries Analysis
Project-URL: Homepage, https://gitlab.com/tue-umphy/software/parmesan
Project-URL: Repository, https://gitlab.com/tue-umphy/software/parmesan
Project-URL: Documentation, https://tue-umphy.gitlab.io/software/parmesan
Project-URL: Changelog, https://gitlab.com/tue-umphy/software/parmesan/-/blob/master/CHANGELOG.md?ref_type=heads
Author-email: Yann Büchau <yann-georb.buechau@uni-tuebingen.de>
License-Expression: GPL-3.0-or-later
License-File: LICENSE
Classifier: Intended Audience :: Science/Research
Classifier: License :: OSI Approved :: GNU General Public License v3 (GPLv3)
Classifier: Topic :: Scientific/Engineering
Requires-Python: <4,>=3.9
Requires-Dist: matplotlib>=3.7.2
Requires-Dist: numpy>=1.13.3
Requires-Dist: pandas>=2
Requires-Dist: pint-pandas>=0.4
Requires-Dist: pint>=0.24.4
Requires-Dist: pip-system-certs>=4.0
Requires-Dist: rich>=13.0
Requires-Dist: scipy>=1.1
Requires-Dist: sympy>=1.12
